aslabs/config/__init__.py
aslabs/config/config.py
aslabs_config-0.0.4.dist-info/WHEEL
aslabs_config-0.0.4.dist-info/METADATA
aslabs_config-0.0.4.dist-info/RECORD
