Metadata-Version: 2.1
Name: aslabs-config
Version: 0.0.4
Summary: Universal configuration system, that maps your env vars, json file and dotenv to dataclass configs
Author: Titusz Ban
Author-email: tituszban@antisociallabs.io
Requires-Python: >=3.9,<4.0
Classifier: Programming Language :: Python :: 3
Classifier: Programming Language :: Python :: 3.9
Classifier: Programming Language :: Python :: 3.10
Classifier: Programming Language :: Python :: 3.11
Requires-Dist: python-dotenv (>=0.21.0,<0.22.0)
